acccmip6/__init__.py
acccmip6/access_cm.py
acccmip6/cli.py
acccmip6/download_dat.py
acccmip6/utilities/CMIP6_database.py
acccmip6/utilities/__init__.py
acccmip6/utilities/c6db.py
acccmip6/utilities/checkers.py
acccmip6/utilities/util.py
acccmip6/utilities/data/CMIP6_exps.xlsx
acccmip6/utilities/data/__init__.py
acccmip6/utilities/data/var_list.xlsx
acccmip6-5.4.0.dist-info/AUTHORS.rst
acccmip6-5.4.0.dist-info/LICENSE
acccmip6-5.4.0.dist-info/METADATA
acccmip6-5.4.0.dist-info/WHEEL
acccmip6-5.4.0.dist-info/entry_points.txt
acccmip6-5.4.0.dist-info/top_level.txt
acccmip6-5.4.0.dist-info/RECORD
