Metadata-Version: 2.1
Name: acccmip6
Version: 5.4.0
Summary: Package for accessing CMIP6 database in real-time
Home-page: https://github.com/TaufiqHassan/acccmip6
Author: Taufiq Hassan
Author-email: taufiq.hassanmozumder@email.ucr.edu
License: MIT
Platform: UNKNOWN
Classifier: License :: OSI Approved :: MIT License
Classifier: Natural Language :: English
Classifier: Programming Language :: Python :: 3.5
Classifier: Programming Language :: Python :: 3.6
Classifier: Programming Language :: Python :: 3.7
License-File: LICENSE
License-File: AUTHORS.rst
Requires-Dist: pandas
Requires-Dist: requests
Requires-Dist: setuptools
Requires-Dist: xlrd
